{
  "id": "analysis_1777820049884_w16km3",
  "status": "completed",
  "input": {
    "type": "file",
    "value": "1777820049877-6ad9972d-fddb-459f-8cf9-2c6bc9e2418f-CN218484462U_______.pdf",
    "fileName": "CN218484462U扫地机器人示例.pdf",
    "fileUrl": "/Users/xiexiaoxiong/Documents/patent/IP-protral/.data/uploads/1777820049877-6ad9972d-fddb-459f-8cf9-2c6bc9e2418f-CN218484462U_______.pdf"
  },
  "steps": [
    {
      "id": 1,
      "name": "专利文本解析",
      "description": "解析专利文件，提取权利要求、说明书和附图",
      "status": "completed",
      "startedAt": 1777820049887,
      "completedAt": 1777820152440
    },
    {
      "id": 2,
      "name": "行业识别与路由",
      "description": "判断专利所属行业，选择对应的关键词生成工作流",
      "status": "completed",
      "startedAt": 1777820152440,
      "completedAt": 1777820152440
    },
    {
      "id": 3,
      "name": "技术关键词生成",
      "description": "基于专利内容生成检索关键词",
      "status": "completed",
      "startedAt": 1777820152440,
      "completedAt": 1777820218544
    },
    {
      "id": 4,
      "name": "商品信息检索",
      "description": "使用关键词检索市场商品信息",
      "status": "error",
      "error": "fetch failed",
      "startedAt": 1777820218544,
      "completedAt": 1777820940933
    },
    {
      "id": 5,
      "name": "技术特征比对",
      "description": "拆解技术特征，进行权利要求-商品特征比对",
      "status": "error",
      "startedAt": 1777820940933,
      "completedAt": 1777820954305
    },
    {
      "id": 6,
      "name": "结果汇总",
      "description": "优先读取工作流响应，并按需回补飞书结果数据",
      "status": "error",
      "error": "无比对结果可写入",
      "completedAt": 1777820954305,
      "startedAt": 1777820954305
    }
  ],
  "results": {
    "dbRecordId": 22,
    "feishuUrl": "",
    "feishuAppToken": "",
    "module1RunId": "fa6f29c1-eda6-4def-aa5c-05c035aebbef",
    "detectedIndustry": "general",
    "industryReasoning": "未命中健身器材或家用电器的高置信度关键词，回退到通用工作流。",
    "keywords": [],
    "keywordRunId": 12,
    "module2RunId": "73441fbb-cb38-43d2-9447-0a7c15387455",
    "industryUsed": "general",
    "products": [],
    "module3Exception": "fetch failed",
    "comparisons": [],
    "claimCompareRunId": 0,
    "module4RunId": "28765c4f-31ee-439c-8a8e-034922ae35ef",
    "module4Exception": "无比对结果可写入"
  },
  "createdAt": 1777820049884,
  "updatedAt": 1777820954305
}